{"sections":{"slideshow":{"type":"slideshow","blocks":{"slide-2":{"type":"image","settings":{"image":"shopify:\/\/shop_images\/luchtige-overhemd-midi-jurk-voor-dames2.webp","subheading":"","title":"<strong>Shop nu voor je nieuwefavoriete kledingstuk!<\/strong>","mobile_text_position":"place-self-center text-center","desktop_text_position":"sm:place-self-center sm:text-center","content_max_width":1200,"button_1_text":"DAMES","button_1_link":"shopify:\/\/collections\/blouses-dames","button_1_style":"solid","button_1_background":"#1c1c1c","button_1_text_color":"#ffffff","button_2_text":"HEREN","button_2_link":"shopify:\/\/collections\/blouses","button_2_style":"solid","button_2_background":"#1c1c1c","button_2_text_color":"#ffffff","background":"#ffffff","background_opacity":0,"text_color":"#ffffff","border_color":"","gradient_overlay":"linear-gradient(180deg, rgba(54, 54, 54, 0.2), rgba(4, 4, 4, 0.65) 100%)"}}},"block_order":["slide-2"],"settings":{"allow_transparent_header":false,"show_next_section_button":false,"media_size":"md","show_initial_transition":false,"autoplay":false,"autoplay_pause_on_video":false,"cycle_speed":4,"background":"#000000","controls_color":"#ffffff"}},"rich_text_rP9eWh":{"type":"rich-text","blocks":{"heading_yEeFn4":{"type":"heading","settings":{"text":"BLACK FRIDAY SALE","heading_tag":"h3"}},"subheading_HTJfBM":{"type":"subheading","settings":{"text":"UP TO 50% OFF"}},"richtext_384PQ8":{"type":"richtext","settings":{"content":"<p>This is the moment to secure our signature menswear pieces at 50% off. Exclusive, refined, and available only for a limited time during the Black Friday period.<\/p><p>2 FOR EXTRA 10% OFF<strong> | <\/strong>3 FOR 20% OFF <strong>|<\/strong> 4+ items 30% OFF <\/p><p>No code needed – discounts apply automatically in cart<\/p>"}}},"block_order":["heading_yEeFn4","subheading_HTJfBM","richtext_384PQ8"],"disabled":true,"name":"t:sections.rich_text.presets.rich_text.name","settings":{"color_scheme":"","separate_section_with_border":true,"content_width":"sm","text_position":"center","remove_vertical_spacing":false}},"featured_collections_wBzncw":{"type":"featured-collections","blocks":{"collection_m9QdtH":{"type":"collection","settings":{"collection":"jurken-dames","products_count":8,"title":"","link_url":"","link_text":"View all"}}},"block_order":["collection_m9QdtH"],"name":"t:sections.featured_collections.presets.featured_collections.name","settings":{"color_scheme":"","separate_section_with_border":false,"hide_product_information":false,"stack_products":false,"products_per_row_mobile":"2","products_per_row_desktop":4,"horizontal_spacing_factor":1,"vertical_spacing_factor":1,"subheading":""}},"featured_product_AheawL":{"type":"featured-product","blocks":{"title_WKmFF7":{"type":"title","settings":{"heading_tag":"h3"}},"badges_fhBGaD":{"type":"badges","settings":{}},"price_mPLafH":{"type":"price","settings":{"show_taxes_notice":false}},"payment_terms_EXWHnf":{"type":"payment_terms","settings":{}},"separator_Ch4nAn":{"type":"separator","settings":{}},"description_aKwEDy":{"type":"description","disabled":true,"settings":{"collapse_content":false}},"variant_picker_qHJBwH":{"type":"variant_picker","disabled":true,"settings":{"hide_sold_out_variants":false,"selector_style":"block","swatch_selector_style":"swatch","variant_image_options":"","size_chart_page":""}},"quantity_selector_ghqTEB":{"type":"quantity_selector","settings":{}},"buy_buttons_84LgMT":{"type":"buy_buttons","settings":{"show_payment_button":false,"show_gift_card_recipient":true,"atc_button_background":"","atc_button_text_color":"","payment_button_background":"","payment_button_text_color":""}},"pickup_availability_JafGXt":{"type":"pickup_availability","settings":{}}},"block_order":["title_WKmFF7","badges_fhBGaD","price_mPLafH","payment_terms_EXWHnf","separator_Ch4nAn","description_aKwEDy","variant_picker_qHJBwH","quantity_selector_ghqTEB","buy_buttons_84LgMT","pickup_availability_JafGXt"],"name":"t:sections.featured_product.presets.featured_product.name","settings":{"color_scheme":"scheme-1","product":"v-hals-blouse-ruches","separate_section_with_border":true,"container_size":"lg","product_info_size":45,"center_basic_info":false,"desktop_media_layout":"carousel_thumbnails_bottom","desktop_media_grid_gap":30,"mobile_controls":"dots","enable_media_autoplay":false,"enable_video_looping":true,"enable_image_zoom":false,"max_image_zoom_level":3,"subheading":"","title":"","content":""}},"collection_list_Yft9aW":{"type":"collection-list","blocks":{"collection_cRajWW":{"type":"collection","settings":{"color_scheme":"","collection":"blazers-dames","image":"shopify:\/\/shop_images\/getailleerde-blazer-met-comfortabele-pasvorm-voor-dames_700x_bf849538-1ec3-400f-856d-eba5343edd08.webp","expand_collection":false,"content_position":"place-self-center text-center","subheading":"","title":"BLAZERS DAMES","button_text":"","button_link":"","button_style":"solid","overlay_color":"#000000","overlay_opacity":0}},"collection_wa8cMY":{"type":"collection","settings":{"color_scheme":"","collection":"blouses-dames","image":"shopify:\/\/shop_images\/dames-top-met-v-hals-en-lange-mouwen15_700x_fb32d639-b8d0-49ff-a93d-69f65379161a.webp","expand_collection":false,"content_position":"place-self-center text-center","subheading":"","title":"BLOUSES DAMES","button_text":"","button_link":"","button_style":"outline","overlay_color":"#000000","overlay_opacity":0}},"collection_N3rYcy":{"type":"collection","settings":{"color_scheme":"","collection":"lange-broeken-dames","image":"shopify:\/\/shop_images\/elegante-rechte-broek-voor-dames-ophelia2_700x_5131ab27-6970-43df-ac1e-15d65c43a2cd.webp","expand_collection":false,"content_position":"place-self-center text-center","subheading":"","title":"BROEKEN DAMES","button_text":"","button_link":"","button_style":"solid","overlay_color":"#000000","overlay_opacity":0}},"collection_CfdRjm":{"type":"collection","settings":{"color_scheme":"scheme-4","collection":"jassen-dames","image":"shopify:\/\/shop_images\/lange-winterjas-voor-dames5_700x_dd083bf4-df68-4ea0-95af-fa2bf8e6fc31.webp","expand_collection":false,"content_position":"place-self-center text-center","subheading":"","title":"JASSEN DAMES","button_text":"","button_link":"","button_style":"solid","overlay_color":"#000000","overlay_opacity":0}},"collection_nbDgVT":{"type":"collection","settings":{"color_scheme":"scheme-4","collection":"jurken-dames","image":"shopify:\/\/shop_images\/elegante-casual-jurk-met-flatterende-pasvorm-voor-dames1_700x_930cb68f-43ef-43b5-a719-b6c0dde2bf20.webp","expand_collection":false,"content_position":"place-self-center text-center","subheading":"","title":"JURKEN DAMES","button_text":"","button_link":"","button_style":"solid","overlay_color":"#000000","overlay_opacity":0}},"collection_WApynV":{"type":"collection","settings":{"color_scheme":"scheme-4","collection":"truien-vesten-dames","image":"shopify:\/\/shop_images\/wollen-damestrui-met-elegante-pasvorm-mireille4_700x_471e4297-09bb-4d5e-a6a1-3a76f9d1b30b.webp","expand_collection":true,"content_position":"place-self-center text-center","subheading":"","title":"TRUIEN & VESTEN DAMES","button_text":"","button_link":"","button_style":"link","overlay_color":"#1c1c1c","overlay_opacity":0}},"collection_jmLMFh":{"type":"collection","settings":{"color_scheme":"scheme-4","collection":"","image":"shopify:\/\/shop_images\/tweedelige-lounge-set-met-broek-en-top-voor-dames2_700x_7ecb011a-de4a-4c01-9251-f0a3fddd1f00.webp","expand_collection":false,"content_position":"place-self-center text-center","subheading":"","title":"SETS DAMES","button_text":"","button_link":"","button_style":"solid","overlay_color":"#000000","overlay_opacity":0}}},"block_order":["collection_cRajWW","collection_wa8cMY","collection_N3rYcy","collection_CfdRjm","collection_nbDgVT","collection_WApynV","collection_jmLMFh"],"name":"t:sections.collection_list.presets.collection_list.name","settings":{"color_scheme":"","separate_section_with_border":true,"image_size":"auto","show_text_outside":false,"space_items":true,"stack_collections":false,"collections_per_row_mobile":"1","collections_per_row_desktop":3,"subheading":"","title":"ONZE DAMES COLLECTIES","content":""}},"featured_product_qTyiNh":{"type":"featured-product","blocks":{"title_7C7JQa":{"type":"title","settings":{"heading_tag":"h3"}},"badges_BnYk7w":{"type":"badges","settings":{}},"price_MTdech":{"type":"price","settings":{"show_taxes_notice":false}},"payment_terms_jGkCfC":{"type":"payment_terms","settings":{}},"separator_jp3QmN":{"type":"separator","settings":{}},"description_xBeApi":{"type":"description","disabled":true,"settings":{"collapse_content":false}},"variant_picker_97mAgN":{"type":"variant_picker","disabled":true,"settings":{"hide_sold_out_variants":false,"selector_style":"block","swatch_selector_style":"swatch","variant_image_options":"","size_chart_page":""}},"quantity_selector_nTyrjq":{"type":"quantity_selector","settings":{}},"buy_buttons_PLkViD":{"type":"buy_buttons","settings":{"show_payment_button":false,"show_gift_card_recipient":true,"atc_button_background":"","atc_button_text_color":"","payment_button_background":"","payment_button_text_color":""}},"pickup_availability_jUiedf":{"type":"pickup_availability","settings":{}}},"block_order":["title_7C7JQa","badges_BnYk7w","price_MTdech","payment_terms_jGkCfC","separator_jp3QmN","description_xBeApi","variant_picker_97mAgN","quantity_selector_nTyrjq","buy_buttons_PLkViD","pickup_availability_jUiedf"],"name":"t:sections.featured_product.presets.featured_product.name","settings":{"color_scheme":"scheme-1","product":"slim-fit-overhemd","separate_section_with_border":true,"container_size":"lg","product_info_size":45,"center_basic_info":false,"desktop_media_layout":"carousel_thumbnails_bottom","desktop_media_grid_gap":30,"mobile_controls":"dots","enable_media_autoplay":false,"enable_video_looping":true,"enable_image_zoom":false,"max_image_zoom_level":3,"subheading":"","title":"","content":""}},"collection_list_6BjE9A":{"type":"collection-list","blocks":{"collection_nfWM67":{"type":"collection","settings":{"color_scheme":"","collection":"korte-broeken-heren","image":"shopify:\/\/shop_images\/sneldrogende-cargo-shorts-voor-heren_700x_00cbe274-12ff-48fd-98ce-39c20641e823.webp","expand_collection":false,"content_position":"place-self-center text-center","subheading":"","title":"BROEKEN HEREN","button_text":"","button_link":"","button_style":"solid","overlay_color":"#000000","overlay_opacity":0}},"collection_ki9pyh":{"type":"collection","settings":{"color_scheme":"","collection":"blouses-dames","image":"shopify:\/\/shop_images\/waterdichte-winterjas-met-warme-voering-voor-heren1_700x_805fec97-7e74-4fe9-8672-f3610a4cc6b4.webp","expand_collection":false,"content_position":"place-self-center text-center","subheading":"","title":"JASSEN HEREN","button_text":"","button_link":"","button_style":"outline","overlay_color":"#000000","overlay_opacity":0}},"collection_7yK7qV":{"type":"collection","settings":{"color_scheme":"","collection":"overhemden-shirts-heren","image":"shopify:\/\/shop_images\/modern-klassiek-overhemd-met-lange-mouwen-voor-heren4_700x_9ba6fbb9-b228-4d9e-9f71-f3aeceb5e7a5.webp","expand_collection":false,"content_position":"place-self-center text-center","subheading":"","title":"OVERHEMDEN & SHIRTS","button_text":"","button_link":"","button_style":"solid","overlay_color":"#000000","overlay_opacity":0}}},"block_order":["collection_nfWM67","collection_ki9pyh","collection_7yK7qV"],"name":"t:sections.collection_list.presets.collection_list.name","settings":{"color_scheme":"","separate_section_with_border":true,"image_size":"auto","show_text_outside":false,"space_items":true,"stack_collections":false,"collections_per_row_mobile":"1","collections_per_row_desktop":3,"subheading":"","title":"ONZE HEREN COLLECTIES","content":""}},"logo_list_Ee3Gkb":{"type":"logo-list","blocks":{"logo_aaxGDe":{"type":"logo","settings":{"logo_width":120,"link":""}},"logo_B7ncQY":{"type":"logo","settings":{"logo_width":80,"link":""}},"logo_AiyPAW":{"type":"logo","settings":{"logo_width":120,"link":""}},"logo_CXUYWH":{"type":"logo","settings":{"logo_width":120,"link":""}}},"block_order":["logo_aaxGDe","logo_B7ncQY","logo_AiyPAW","logo_CXUYWH"],"disabled":true,"name":"t:sections.logo_list.presets.logo_list.name","settings":{"color_scheme":"","separate_section_with_border":true,"subheading":"inspired by","title":"","items_per_row":5,"logo_item_background":"","logo_item_border":""}},"multi_column_6trqqH":{"type":"multi-column","blocks":{"image_with_text_B4TwFK":{"type":"image_with_text","settings":{"title":"ABOUT","heading_tag":"h6","content":"<p>Lucien Moreno designs refined everyday pieces defined by expert craftsmanship, clean silhouettes, and premium natural materials — including Cloudwool®, cashmere, and supple sheep suede. Crafted with intention, each piece is made to last, feel exceptional, and elevate the everyday through quiet, timeless design.<\/p>","link_url":"shopify:\/\/pages\/about","link_text":""}},"image_with_text_EiXpEg":{"type":"image_with_text","settings":{"title":"CLOUDWOOL®","heading_tag":"h6","content":"<p>Cloudwool® combines ultrafine softness with lightweight warmth. Developed using carefully selected Australian wool fibers, it reflects a modern approach to knitwear — blending high-quality natural material with comfort and clarity. The result is a breathable, refined knit built for year-round wear.<\/p>","link_url":"shopify:\/\/pages\/cloudwool","link_text":"Learn more"}},"image_with_text_J8dbjQ":{"type":"image_with_text","settings":{"title":"LINEN","heading_tag":"h6","content":"<p>Lucien Moreno’s linen is woven from responsibly sourced European flax and selected for its lightness, breathability, and soft, textured feel. Naturally cooling and easy to wear, it brings comfort and calm structure to warmer days. Whether styled for relaxed escapes or everyday use, it offers refined versatility — elevated in quality, and grounded in nature.<\/p>","link_url":"shopify:\/\/pages\/linen","link_text":"Learn more"}},"image_with_text_rjcp3R":{"type":"image_with_text","settings":{"title":"CASHMERE","heading_tag":"h6","content":"<p>In the remote desert region of Alxa, Inner Mongolia, a rare and exquisite treasure is found. Known for producing some of the world’s finest cashmere, Alxa is home to a unique breed of goats that grow an exceptionally soft undercoat. This undercoat — a thin fleece layer around the roots of the goat's hair — grows during the coldest months and naturally sheds in spring, allowing for ethical and sustainable collection.<\/p>","link_url":"shopify:\/\/pages\/cashmere","link_text":""}},"image_with_text_6eC4kW":{"type":"image_with_text","settings":{"title":"Suède","heading_tag":"h6","content":"<p>The Moreno Sheep Suede is soft, matte, and smooth to the touch. Treated with a special oiling technique, it’s made to hold its colour and develop depth over time. It feels lived-in from the first wear, and only gets better with age.<\/p>","link_url":"shopify:\/\/pages\/suede","link_text":"Learn more"}}},"block_order":["image_with_text_B4TwFK","image_with_text_EiXpEg","image_with_text_J8dbjQ","image_with_text_rjcp3R","image_with_text_6eC4kW"],"disabled":true,"name":"t:sections.multi_column.presets.multi_column.name","settings":{"color_scheme":"scheme-2","separate_section_with_border":true,"columns_per_row":5,"stack_on_mobile":false,"overlap_image":false,"content_alignment":"start","text_alignment":"start","spacing":"xs","subheading":"","title":"","content":""}},"ss_instafeed_2_Q7RXtL":{"type":"ss-instafeed-2","blocks":{"slide_cmBH6y":{"type":"slide","settings":{"url":""}},"slide_EakQzW":{"type":"slide","settings":{"url":""}},"slide_Kh7rW9":{"type":"slide","settings":{"url":""}},"slide_Br3jtU":{"type":"slide","settings":{"url":""}},"slide_ffdFmQ":{"type":"slide","settings":{"url":""}},"slide_GjN3pP":{"type":"slide","settings":{"url":""}}},"block_order":["slide_cmBH6y","slide_EakQzW","slide_Kh7rW9","slide_Br3jtU","slide_ffdFmQ","slide_GjN3pP"],"disabled":true,"name":"SS - Instafeed #2","settings":{"top":"","top_custom":false,"top_font":"josefin_sans_n4","top_size":13,"top_height":130,"top_align":"center","heading":"","heading_custom":false,"heading_font":"josefin_sans_n4","heading_size":40,"heading_height":130,"heading_align":"center","heading_mt":12,"subheading":"<h3><strong>TAG US TO GET FEATURED<\/strong><\/h3>","subheading_custom":true,"subheading_font":"montserrat_n4","subheading_size":12,"subheading_height":130,"subheading_align":"center","subheading_mt":12,"slider_mt":60,"slider_row":"3","slider_row_mobile":"2","slider_gap":8,"slider_gap_mobile":4,"autoplay":true,"autoplay_speed":10,"nav_size":40,"nav_size_mobile":30,"hide_nav":true,"hide_nav_mobile":false,"image_radius":0,"top_color":"#1c1c1c","heading_color":"#746661","subheading_color":"#1c1c1c","nav_btn_bg":"rgba(0,0,0,0)","nav_btn_hover_bg":"rgba(0,0,0,0)","nav_border":"rgba(0,0,0,0)","nav_border_hover":"rgba(0,0,0,0)","nav_icon":"#ffffff","nav_hover_icon":"#ffffff","background_color":"#ffffff","background_gradient":"","border_color":"#000000","margin_top":0,"margin_bottom":0,"padding_top":36,"padding_bottom":36,"padding_horizontal":5,"padding_horizontal_mobile":1.5,"full_width":true,"content_width":120,"border_thickness":0,"lazy":true}}},"order":["slideshow","rich_text_rP9eWh","featured_collections_wBzncw","featured_product_AheawL","collection_list_Yft9aW","featured_product_qTyiNh","collection_list_6BjE9A","logo_list_Ee3Gkb","multi_column_6trqqH","ss_instafeed_2_Q7RXtL"]}